{
    "DNDConfig": null,
    "__parentReadjusting__": false,
    "_height_": {
        "type": "string",
        "value": "10%"
    },
    "_margin_": [
        0,
        0,
        0,
        0
    ],
    "_orientation_": 6,
    "_padding_": [
        0,
        0,
        0,
        0
    ],
    "_percent_": true,
    "_skin_": "sdcfc8dd0a004413afb690d1a85a07f9",
    "_top_": {
        "type": "string",
        "value": "5%"
    },
    "_width_": {
        "type": "string",
        "value": "80%"
    },
    "allboxes": [],
    "autogrowmode": 0,
    "canUpdateUI": true,
    "centerx": {
        "type": "string",
        "value": "50%"
    },
    "children": [
        "txtPassword",
        "txtPassText",
        "flxGaris2",
        "flxCek"
    ],
    "clipbounds": true,
    "containerweight": 100,
    "enablescrolling": true,
    "id": "flxPassword",
    "info": null,
    "isvisible": true,
    "kuid": "i269f079eef344a8818faaf8b81c3fa6",
    "layouttype": 2,
    "name": "kony.ui.FlexContainer",
    "parent": "flxIsi",
    "pf": "frmPilihWifiDevice",
    "snapgridsize": 10,
    "snaptogrid": true,
    "wType": "FlexContainer",
    "widgetalignment": 1,
    "zindex": 1
}